dataknobs_structures/__init__.py
dataknobs_structures/conditional_dict.py
dataknobs_structures/document.py
dataknobs_structures/py.typed
dataknobs_structures/record_store.py
dataknobs_structures/tree.py
dataknobs_structures-1.0.5.dist-info/METADATA
dataknobs_structures-1.0.5.dist-info/WHEEL
dataknobs_structures-1.0.5.dist-info/RECORD
