Metadata-Version: 2.4
Name: dataknobs-structures
Version: 1.0.5
Summary: Data structures for AI knowledge bases
Author-email: Spence Koehler <KoehlerSB747@gmail.com>
Requires-Python: >=3.10
Requires-Dist: dataknobs-common>=1.0.0
Requires-Dist: graphviz>=0.20.3
Requires-Dist: pandas>=2.2.3
Requires-Dist: pyparsing>=3.0.0
